mafia/__init__.py
mafia/action_base.py
mafia/action_helpers.py
mafia/actions.py
mafia/alignment.py
mafia/day.py
mafia/effects.py
mafia/events.py
mafia/exceptions.py
mafia/factions.py
mafia/game.py
mafia/log.py
mafia/mixin.py
mafia/night.py
mafia/parser.py
mafia/phase.py
mafia/placeholders.py
mafia/player.py
mafia/roles.py
mafia/util.py
mafia/virtual_actions.py
mafia-1.0.0.dist-info/DESCRIPTION.rst
mafia-1.0.0.dist-info/METADATA
mafia-1.0.0.dist-info/RECORD
mafia-1.0.0.dist-info/WHEEL
mafia-1.0.0.dist-info/metadata.json
mafia-1.0.0.dist-info/top_level.txt
mafia-1.0.0.dist-info/zip-safe
