Metadata-Version: 2.0
Name: mafia
Version: 1.0.0
Summary: A library for moderating games of Mafia.
Home-page: https://github.com/calder/mafia
Author: Calder Coalson
Author-email: caldercoalson@gmail.com
License: UNKNOWN
Platform: UNKNOWN
Requires-Dist: termcolor
